framcore/Base.py
framcore/Model.py
framcore/__init__.py
framcore/aggregators/Aggregator.py
framcore/aggregators/HydroAggregator.py
framcore/aggregators/NodeAggregator.py
framcore/aggregators/WindSolarAggregator.py
framcore/aggregators/__init__.py
framcore/aggregators/_utils.py
framcore/attributes/Arrow.py
framcore/attributes/ElasticDemand.py
framcore/attributes/ReservoirCurve.py
framcore/attributes/SoftBound.py
framcore/attributes/StartUpCost.py
framcore/attributes/Storage.py
framcore/attributes/TargetBound.py
framcore/attributes/__init__.py
framcore/attributes/hydro/HydroBypass.py
framcore/attributes/hydro/HydroGenerator.py
framcore/attributes/hydro/HydroPump.py
framcore/attributes/hydro/HydroReservoir.py
framcore/attributes/hydro/__init__.py
framcore/attributes/level_profile_attributes.py
framcore/components/Component.py
framcore/components/Demand.py
framcore/components/Flow.py
framcore/components/HydroModule.py
framcore/components/Node.py
framcore/components/Thermal.py
framcore/components/Transmission.py
framcore/components/_PowerPlant.py
framcore/components/__init__.py
framcore/components/wind_solar.py
framcore/curves/Curve.py
framcore/curves/LoadedCurve.py
framcore/curves/__init__.py
framcore/events/__init__.py
framcore/events/events.py
framcore/expressions/Expr.py
framcore/expressions/__init__.py
framcore/expressions/_get_constant_from_expr.py
framcore/expressions/_utils.py
framcore/expressions/queries.py
framcore/expressions/units.py
framcore/fingerprints/__init__.py
framcore/fingerprints/fingerprint.py
framcore/juliamodels/JuliaModel.py
framcore/juliamodels/__init__.py
framcore/loaders/__init__.py
framcore/loaders/loaders.py
framcore/metadata/Div.py
framcore/metadata/ExprMeta.py
framcore/metadata/LevelExprMeta.py
framcore/metadata/Member.py
framcore/metadata/Meta.py
framcore/metadata/__init__.py
framcore/populators/Populator.py
framcore/populators/__init__.py
framcore/querydbs/CacheDB.py
framcore/querydbs/ModelDB.py
framcore/querydbs/QueryDB.py
fram_core-0.1.0.dist-info/METADATA
fram_core-0.1.0.dist-info/WHEEL
fram_core-0.1.0.dist-info/licenses/LICENSE.md
fram_core-0.1.0.dist-info/RECORD
